pvtm/__init__.py
pvtm/pvtm.py
pvtm/data/sample_5000.csv
pvtm_temp-1.0.0.dist-info/METADATA
pvtm_temp-1.0.0.dist-info/WHEEL
pvtm_temp-1.0.0.dist-info/top_level.txt
pvtm_temp-1.0.0.dist-info/RECORD
