Metadata-Version: 2.1
Name: pvtm-temp
Version: 1.0.0
Summary: Topic Modeling with doc2vec and Gaussian mixture clustering
Home-page: UNKNOWN
Author: David Lenz
Author-email: david.lenz@wi.jlug.de
License: MIT
Platform: UNKNOWN
